{
  "openapi": "3.0.0",
  "info": {
    "title": "Loan API",
    "version": "3.0.0",
    "x-api-id": "loan-api-v3",
    "x-api-version": "v3",
    "x-status": "active",
    "x-team": "Equipe Banque",
    "x-domain": "Banking",
    "description": "Prets personnels et professionnels. Decision IA et echeancier. DIFFERENCE vs mortgage-api : Loan = pret personnel sans garantie, Mortgage = pret immobilier avec hypotheque.",
    "x-false-positive-warning": "Pret immobilier -> mortgage-api-v2.",
    "x-breaking-changes-from-previous": [
      "Decision IA",
      "Remboursement anticipe"
    ]
  },
  "servers": [
    {
      "url": "http://localhost:8000",
      "description": "Kong API Gateway"
    }
  ],
  "paths": {
    "/v3/loans": {
      "get": {
        "summary": "Portefeuille",
        "operationId": "listLoansV3",
        "tags": [
          "Loans"
        ],
        "responses": {
          "200": {
            "description": "OK"
          }
        },
        "security": [
          {
            "ApiKeyAuth": []
          }
        ]
      },
      "post": {
        "summary": "Demander",
        "operationId": "applyLoanV3",
        "tags": [
          "Loans"
        ],
        "responses": {
          "200": {
            "description": "OK"
          }
        },
        "security": [
          {
            "ApiKeyAuth": []
          }
        ]
      }
    },
    "/v3/loans/{id}": {
      "parameters": [
        {
          "name": "id",
          "in": "path",
          "required": true,
          "schema": {
            "type": "string"
          }
        }
      ],
      "get": {
        "summary": "Detail",
        "operationId": "getLoanV3",
        "tags": [
          "Loans"
        ],
        "responses": {
          "200": {
            "description": "OK"
          }
        },
        "security": [
          {
            "ApiKeyAuth": []
          }
        ]
      },
      "put": {
        "summary": "Modifier",
        "operationId": "updateLoan",
        "tags": [
          "Loans"
        ],
        "responses": {
          "200": {
            "description": "OK"
          }
        },
        "security": [
          {
            "ApiKeyAuth": []
          }
        ]
      }
    },
    "/v3/loans/{id}/repayments": {
      "parameters": [
        {
          "name": "id",
          "in": "path",
          "required": true,
          "schema": {
            "type": "string"
          }
        }
      ],
      "get": {
        "summary": "Echeancier",
        "operationId": "getRepaymentSchedule",
        "tags": [
          "Repayments"
        ],
        "responses": {
          "200": {
            "description": "OK"
          }
        },
        "security": [
          {
            "ApiKeyAuth": []
          }
        ]
      },
      "post": {
        "summary": "Rembourser",
        "operationId": "makeRepayment",
        "tags": [
          "Repayments"
        ],
        "responses": {
          "200": {
            "description": "OK"
          }
        },
        "security": [
          {
            "ApiKeyAuth": []
          }
        ]
      }
    },
    "/v3/loans/simulate": {
      "post": {
        "summary": "Simuler",
        "operationId": "simulateLoanV3",
        "tags": [
          "Simulation"
        ],
        "responses": {
          "200": {
            "description": "OK"
          }
        },
        "security": [
          {
            "ApiKeyAuth": []
          }
        ]
      }
    },
    "/v3/loans/{id}/early-repayment": {
      "parameters": [
        {
          "name": "id",
          "in": "path",
          "required": true,
          "schema": {
            "type": "string"
          }
        }
      ],
      "post": {
        "summary": "Remboursement anticipe",
        "operationId": "earlyRepay",
        "tags": [
          "EarlyRepay"
        ],
        "responses": {
          "200": {
            "description": "OK"
          }
        },
        "security": [
          {
            "ApiKeyAuth": []
          }
        ]
      }
    }
  },
  "components": {
    "schemas": {
      "Error": {
        "type": "object",
        "properties": {
          "code": {
            "type": "string"
          },
          "message": {
            "type": "string"
          }
        }
      }
    },
    "securitySchemes": {
      "ApiKeyAuth": {
        "type": "apiKey",
        "in": "header",
        "name": "X-API-Key"
      }
    }
  }
}